lambda_cloud_api_client/__init__.py
lambda_cloud_api_client/api/__init__.py
lambda_cloud_api_client/api/default/__init__.py
lambda_cloud_api_client/api/default/add_ssh_key.py
lambda_cloud_api_client/api/default/delete_ssh_key.py
lambda_cloud_api_client/api/default/get_instance.py
lambda_cloud_api_client/api/default/instance_types.py
lambda_cloud_api_client/api/default/launch_instance.py
lambda_cloud_api_client/api/default/list_file_systems.py
lambda_cloud_api_client/api/default/list_instances.py
lambda_cloud_api_client/api/default/list_ssh_keys.py
lambda_cloud_api_client/api/default/restart_instance.py
lambda_cloud_api_client/api/default/terminate_instance.py
lambda_cloud_api_client/client.py
lambda_cloud_api_client/errors.py
lambda_cloud_api_client/models/__init__.py
lambda_cloud_api_client/models/add_ssh_key_body.py
lambda_cloud_api_client/models/error.py
lambda_cloud_api_client/models/error_code.py
lambda_cloud_api_client/models/error_response_body.py
lambda_cloud_api_client/models/error_response_body_field_errors.py
lambda_cloud_api_client/models/file_system.py
lambda_cloud_api_client/models/instance.py
lambda_cloud_api_client/models/instance_status.py
lambda_cloud_api_client/models/instance_type.py
lambda_cloud_api_client/models/instance_type_specs.py
lambda_cloud_api_client/models/launch_instance_body.py
lambda_cloud_api_client/models/region.py
lambda_cloud_api_client/models/restart_instance_body.py
lambda_cloud_api_client/models/ssh_key.py
lambda_cloud_api_client/models/terminate_instance_body.py
lambda_cloud_api_client/models/user.py
lambda_cloud_api_client/models/user_status.py
lambda_cloud_api_client/py.typed
lambda_cloud_api_client/types.py
lambda_cloud_api_client-0.1.140.dist-info/METADATA
lambda_cloud_api_client-0.1.140.dist-info/WHEEL
lambda_cloud_api_client-0.1.140.dist-info/RECORD
